{
	"parent": "minecraft:recipes/root",
	"criteria": {
		"has_item": {
			"trigger": "minecraft:inventory_changed",
			"conditions": {
				"items": [
					{
						"item": "biomemakeover:brown_mushroom_brick"
					}
				]
			}
		},
		"has_the_recipe": {
			"trigger": "minecraft:recipe_unlocked",
			"conditions": {
				"recipe": "biomemakeover:brown_mushroom_brick_slab_stonecutting"
			}
		}
	},
	"requirements": [
		[
			"has_item",
			"has_the_recipe"
		]
	],
	"rewards": {
		"recipes": [
			"biomemakeover:brown_mushroom_brick_slab_stonecutting"
		]
	}
}